README.md
setup.cfg
setup.py
dist2809/Binomialdistribution.py
dist2809/Gaussiandistribution.py
dist2809/Generaldistribution.py
dist2809/__init__.py
distributions_yz.egg-info/PKG-INFO
distributions_yz.egg-info/SOURCES.txt
distributions_yz.egg-info/dependency_links.txt
distributions_yz.egg-info/not-zip-safe
distributions_yz.egg-info/top_level.txt